{
    "currentGold": 1.2999999999588444e+16,
    "currentStage": 11,
    "currentTheme": 3,
    "dataFragments": 582,
    "equippedIds": [
        39,
        39,
        115,
        14,
        39
    ],
    "heroLevels": [
        1,
        4,
        20,
        1
    ],
    "hiredRoles": [
        0,
        1,
        2,
        4,
        1,
        1,
        1,
        1,
        1,
        1,
        1,
        1,
        1,
        1,
        1,
        1,
        1,
        1,
        2,
        2,
        2,
        2,
        2,
        2,
        2,
        4,
        4
    ],
    "inventory": [
        {
            "atkMul": 0.04749999940395355,
            "flavorText": "",
            "hpMul": 0.03200000151991844,
            "id": 1,
            "name": "コンデンサ (Lv2)",
            "rarity": 0,
            "spdMul": 0.012500000186264515,
            "type": 2
        },
        {
            "atkMul": 0.023000000044703484,
            "flavorText": "",
            "hpMul": 0.03700000047683716,
            "id": 2,
            "name": "コンデンサ (Lv3)",
            "rarity": 1,
            "spdMul": 0.09600000083446503,
            "type": 2
        },
        {
            "atkMul": 0.04800000041723251,
            "flavorText": "",
            "hpMul": 0.020000001415610313,
            "id": 3,
            "name": "コンデンサ (Lv4)",
            "rarity": 0,
            "spdMul": 0.036500003188848495,
            "type": 2
        },
        {
            "atkMul": 0.14999999105930328,
            "flavorText": "",
            "hpMul": 0.13499999046325684,
            "id": 4,
            "name": "LANケーブル (Lv5)",
            "rarity": 0,
            "spdMul": 0.11999999731779099,
            "type": 4
        },
        {
            "atkMul": 0.11969999969005585,
            "flavorText": "",
            "hpMul": 0.10080000758171082,
            "id": 5,
            "name": "USBメモリ (Lv1)",
            "rarity": 1,
            "spdMul": 0.08400000631809235,
            "type": 0
        },
        {
            "atkMul": 0.11445000767707825,
            "flavorText": "",
            "hpMul": 0.10080000758171082,
            "id": 6,
            "name": "コンデンサ (Lv1)",
            "rarity": 1,
            "spdMul": 0.09765000641345978,
            "type": 2
        },
        {
            "atkMul": 0.10530000925064087,
            "flavorText": "",
            "hpMul": 0.10530000925064087,
            "id": 7,
            "name": "USBメモリ (Lv2)",
            "rarity": 0,
            "spdMul": 0.10260000079870224,
            "type": 0
        },
        {
            "atkMul": 0.3112499713897705,
            "flavorText": "",
            "hpMul": 0.35249996185302734,
            "id": 8,
            "name": "冷却ファン (Lv10)",
            "rarity": 1,
            "spdMul": 0.3937499523162842,
            "type": 3
        },
        {
            "atkMul": 0.3622499406337738,
            "flavorText": "",
            "hpMul": 0.40709999203681946,
            "id": 9,
            "name": "冷却ファン (Lv9)",
            "rarity": 1,
            "spdMul": 0.32429996132850647,
            "type": 3
        },
        {
            "atkMul": 0.08190000802278519,
            "flavorText": "",
            "hpMul": 0.06440000236034393,
            "id": 10,
            "name": "冷却ファン (Lv1)",
            "rarity": 0,
            "spdMul": 0.08190000802278519,
            "type": 3
        },
        {
            "atkMul": 0.40709999203681946,
            "flavorText": "",
            "hpMul": 0.28289997577667236,
            "id": 11,
            "name": "冷却ファン (Lv9)",
            "rarity": 1,
            "spdMul": 0.38294997811317444,
            "type": 3
        },
        {
            "atkMul": 0.18149998784065247,
            "flavorText": "",
            "hpMul": 0.16499999165534973,
            "id": 12,
            "name": "コンデンサ (Lv3)",
            "rarity": 1,
            "spdMul": 0.17819999158382416,
            "type": 2
        },
        {
            "atkMul": 0.1972000151872635,
            "flavorText": "",
            "hpMul": 0.1632000058889389,
            "id": 13,
            "name": "LANケーブル (Lv6)",
            "rarity": 0,
            "spdMul": 0.15980000793933868,
            "type": 4
        },
        {
            "atkMul": 0.34439998865127563,
            "flavorText": "",
            "hpMul": 0.46619999408721924,
            "id": 14,
            "name": "冷却ファン (Lv8)",
            "rarity": 2,
            "spdMul": 0.335999995470047,
            "type": 3
        },
        {
            "atkMul": 0.1581999957561493,
            "flavorText": "",
            "hpMul": 0.1624000072479248,
            "id": 15,
            "name": "拡張基板 (Lv1)",
            "rarity": 2,
            "spdMul": 0.13580000400543213,
            "type": 1
        },
        {
            "atkMul": 0.1784999966621399,
            "flavorText": "",
            "hpMul": 0.14249999821186066,
            "id": 16,
            "name": "冷却ファン (Lv5)",
            "rarity": 0,
            "spdMul": 0.15449999272823334,
            "type": 3
        },
        {
            "atkMul": 0.11180000007152557,
            "flavorText": "",
            "hpMul": 0.1404000073671341,
            "id": 17,
            "name": "コンデンサ (Lv4)",
            "rarity": 0,
            "spdMul": 0.11309999972581863,
            "type": 2
        },
        {
            "atkMul": 0.21209998428821564,
            "flavorText": "",
            "hpMul": 0.19739998877048492,
            "id": 18,
            "name": "コンデンサ (Lv8)",
            "rarity": 0,
            "spdMul": 0.2393999844789505,
            "type": 2
        },
        {
            "atkMul": 0.19999998807907104,
            "flavorText": "",
            "hpMul": 0.26749998331069946,
            "id": 19,
            "name": "冷却ファン (Lv10)",
            "rarity": 0,
            "spdMul": 0.28999999165534973,
            "type": 3
        },
        {
            "atkMul": 0.18479999899864197,
            "flavorText": "",
            "hpMul": 0.2199999988079071,
            "id": 20,
            "name": "拡張基板 (Lv3)",
            "rarity": 2,
            "spdMul": 0.2287999838590622,
            "type": 1
        },
        {
            "atkMul": 0.17999999225139618,
            "flavorText": "",
            "hpMul": 0.1469999998807907,
            "id": 21,
            "name": "コンデンサ (Lv5)",
            "rarity": 0,
            "spdMul": 0.13650000095367432,
            "type": 2
        },
        {
            "atkMul": 0.22499999403953552,
            "flavorText": "",
            "hpMul": 0.25200000405311584,
            "id": 22,
            "name": "LANケーブル (Lv5)",
            "rarity": 1,
            "spdMul": 0.20925000309944153,
            "type": 4
        },
        {
            "atkMul": 0.07740000635385513,
            "flavorText": "",
            "hpMul": 0.0746999979019165,
            "id": 23,
            "name": "コンデンサ (Lv2)",
            "rarity": 0,
            "spdMul": 0.09180000424385071,
            "type": 2
        },
        {
            "atkMul": 0.18859998881816864,
            "flavorText": "",
            "hpMul": 0.26910001039505005,
            "id": 24,
            "name": "冷却ファン (Lv9)",
            "rarity": 0,
            "spdMul": 0.19550000131130219,
            "type": 3
        },
        {
            "atkMul": 0.05739999935030937,
            "flavorText": "",
            "hpMul": 0.062300000339746475,
            "id": 25,
            "name": "冷却ファン (Lv1)",
            "rarity": 0,
            "spdMul": 0.0608999989926815,
            "type": 3
        },
        {
            "atkMul": 0.06720000505447388,
            "flavorText": "",
            "hpMul": 0.06720000505447388,
            "id": 26,
            "name": "冷却ファン (Lv1)",
            "rarity": 0,
            "spdMul": 0.07560000568628311,
            "type": 3
        },
        {
            "atkMul": 0.17429998517036438,
            "flavorText": "",
            "hpMul": 0.22049997746944427,
            "id": 27,
            "name": "冷却ファン (Lv8)",
            "rarity": 0,
            "spdMul": 0.23099999129772186,
            "type": 3
        },
        {
            "atkMul": 0.15080000460147858,
            "flavorText": "",
            "hpMul": 0.1078999936580658,
            "id": 28,
            "name": "拡張基板 (Lv4)",
            "rarity": 0,
            "spdMul": 0.10399999469518661,
            "type": 1
        },
        {
            "atkMul": 0.10080000758171082,
            "flavorText": "",
            "hpMul": 0.07830000668764114,
            "id": 29,
            "name": "コンデンサ (Lv2)",
            "rarity": 0,
            "spdMul": 0.08190000802278519,
            "type": 2
        },
        {
            "atkMul": 0.5197999477386475,
            "flavorText": "",
            "hpMul": 0.49219998717308044,
            "id": 30,
            "name": "拡張基板 (Lv9)",
            "rarity": 2,
            "spdMul": 0.4829999506473541,
            "type": 1
        },
        {
            "atkMul": 0.280349999666214,
            "flavorText": "",
            "hpMul": 0.33705002069473267,
            "id": 31,
            "name": "コンデンサ (Lv8)",
            "rarity": 1,
            "spdMul": 0.33705002069473267,
            "type": 2
        },
        {
            "atkMul": 0.1843000054359436,
            "flavorText": "",
            "hpMul": 0.21849998831748962,
            "id": 32,
            "name": "コンデンサ (Lv7)",
            "rarity": 0,
            "spdMul": 0.19569998979568481,
            "type": 2
        },
        {
            "atkMul": 0.12610000371932983,
            "flavorText": "",
            "hpMul": 0.11569999158382416,
            "id": 33,
            "name": "冷却ファン (Lv4)",
            "rarity": 0,
            "spdMul": 0.15210001170635223,
            "type": 3
        },
        {
            "atkMul": 0.3889999985694885,
            "flavorText": "強力だがウイルスが混入している。",
            "hpMul": -0.10000000149011612,
            "id": 34,
            "name": "[感染] LANケーブル (Lv2)",
            "rarity": 2,
            "spdMul": 0.2070000022649765,
            "type": 4
        },
        {
            "atkMul": 0.14790000021457672,
            "flavorText": "",
            "hpMul": 0.19550000131130219,
            "id": 35,
            "name": "LANケーブル (Lv6)",
            "rarity": 0,
            "spdMul": 0.16830000281333923,
            "type": 4
        },
        {
            "atkMul": 0.23919998109340668,
            "flavorText": "",
            "hpMul": 0.2092999964952469,
            "id": 36,
            "name": "コンデンサ (Lv9)",
            "rarity": 0,
            "spdMul": 0.18400000035762787,
            "type": 2
        },
        {
            "atkMul": 0.133899986743927,
            "flavorText": "",
            "hpMul": 0.11959999799728394,
            "id": 37,
            "name": "USBメモリ (Lv4)",
            "rarity": 0,
            "spdMul": 0.11309999972581863,
            "type": 0
        },
        {
            "atkMul": 0.09870000183582306,
            "flavorText": "",
            "hpMul": 0.10080000758171082,
            "id": 38,
            "name": "USBメモリ (Lv1)",
            "rarity": 1,
            "spdMul": 0.1071000024676323,
            "type": 0
        },
        {
            "atkMul": 0.4334999918937683,
            "flavorText": "",
            "hpMul": 0.6119999885559082,
            "id": 39,
            "name": "拡張基板 (Lv6)",
            "rarity": 3,
            "spdMul": 0.5252999663352966,
            "type": 1
        },
        {
            "atkMul": 0.16050000488758087,
            "flavorText": "",
            "hpMul": 0.13499999046325684,
            "id": 40,
            "name": "拡張基板 (Lv5)",
            "rarity": 0,
            "spdMul": 0.16200000047683716,
            "type": 1
        },
        {
            "atkMul": 0.15149998664855957,
            "flavorText": "",
            "hpMul": 0.14099998772144318,
            "id": 41,
            "name": "コンデンサ (Lv5)",
            "rarity": 0,
            "spdMul": 0.17099998891353607,
            "type": 2
        },
        {
            "atkMul": 0.19110000133514404,
            "flavorText": "",
            "hpMul": 0.24570000171661377,
            "id": 42,
            "name": "USBメモリ (Lv8)",
            "rarity": 0,
            "spdMul": 0.1784999966621399,
            "type": 0
        },
        {
            "atkMul": 0.11829999834299088,
            "flavorText": "",
            "hpMul": 0.12350000441074371,
            "id": 43,
            "name": "LANケーブル (Lv4)",
            "rarity": 0,
            "spdMul": 0.12610000371932983,
            "type": 4
        },
        {
            "atkMul": 0.12870000302791595,
            "flavorText": "",
            "hpMul": 0.12760001420974731,
            "id": 44,
            "name": "USBメモリ (Lv3)",
            "rarity": 0,
            "spdMul": 0.11990000307559967,
            "type": 0
        },
        {
            "atkMul": 0.22950001060962677,
            "flavorText": "",
            "hpMul": 0.22694998979568481,
            "id": 45,
            "name": "コンデンサ (Lv6)",
            "rarity": 1,
            "spdMul": 0.2549999952316284,
            "type": 2
        },
        {
            "atkMul": 0.11445000767707825,
            "flavorText": "",
            "hpMul": 0.10080000758171082,
            "id": 46,
            "name": "コンデンサ (Lv1)",
            "rarity": 1,
            "spdMul": 0.09765000641345978,
            "type": 2
        },
        {
            "atkMul": 0.1264999955892563,
            "flavorText": "",
            "hpMul": 0.1264999955892563,
            "id": 47,
            "name": "拡張基板 (Lv3)",
            "rarity": 0,
            "spdMul": 0.09459999948740005,
            "type": 1
        },
        {
            "atkMul": 0.11070000380277634,
            "flavorText": "",
            "hpMul": 0.11340001225471497,
            "id": 48,
            "name": "LANケーブル (Lv2)",
            "rarity": 1,
            "spdMul": 0.11745000630617142,
            "type": 4
        },
        {
            "atkMul": 0.25499996542930603,
            "flavorText": "",
            "hpMul": 0.21249999105930328,
            "id": 49,
            "name": "LANケーブル (Lv10)",
            "rarity": 0,
            "spdMul": 0.20749998092651367,
            "type": 4
        },
        {
            "atkMul": 0.08190000802278519,
            "flavorText": "",
            "hpMul": 0.06509999930858612,
            "id": 50,
            "name": "USBメモリ (Lv1)",
            "rarity": 0,
            "spdMul": 0.06440000236034393,
            "type": 0
        },
        {
            "atkMul": 0.40279996395111084,
            "flavorText": "",
            "hpMul": 0.4560000002384186,
            "id": 51,
            "name": "LANケーブル (Lv7)",
            "rarity": 2,
            "spdMul": 0.42559999227523804,
            "type": 4
        },
        {
            "atkMul": 0.1972000151872635,
            "flavorText": "",
            "hpMul": 0.1972000151872635,
            "id": 52,
            "name": "冷却ファン (Lv6)",
            "rarity": 0,
            "spdMul": 0.19040000438690186,
            "type": 3
        },
        {
            "atkMul": 0.42879998683929443,
            "flavorText": "強力だがウイルスが混入している。",
            "hpMul": -0.10000000149011612,
            "id": 53,
            "name": "[感染] コンデンサ (Lv4)",
            "rarity": 2,
            "spdMul": 0.29457998275756836,
            "type": 2
        },
        {
            "atkMul": 0.22374001145362854,
            "flavorText": "",
            "hpMul": 0.22968003153800964,
            "id": 54,
            "name": "拡張基板 (Lv2)",
            "rarity": 2,
            "spdMul": 0.19206002354621887,
            "type": 1
        },
        {
            "atkMul": 0.2821500301361084,
            "flavorText": "",
            "hpMul": 0.2790150046348572,
            "id": 55,
            "name": "コンデンサ (Lv7)",
            "rarity": 1,
            "spdMul": 0.3135000169277191,
            "type": 2
        },
        {
            "atkMul": 0.09539999812841415,
            "flavorText": "",
            "hpMul": 0.10440000891685486,
            "id": 56,
            "name": "冷却ファン (Lv2)",
            "rarity": 0,
            "spdMul": 0.08820000290870667,
            "type": 3
        },
        {
            "atkMul": 0.940750777721405,
            "flavorText": "",
            "hpMul": 0.8087155818939209,
            "id": 57,
            "name": "拡張基板 (Lv13)",
            "rarity": 2,
            "spdMul": 0.8747331500053406,
            "type": 1
        },
        {
            "atkMul": 0.30043330788612366,
            "flavorText": "",
            "hpMul": 0.333814799785614,
            "id": 58,
            "name": "USBメモリ (Lv7)",
            "rarity": 0,
            "spdMul": 0.27817898988723755,
            "type": 0
        },
        {
            "atkMul": 0.4895950257778168,
            "flavorText": "",
            "hpMul": 0.6175573468208313,
            "id": 59,
            "name": "USBメモリ (Lv7)",
            "rarity": 2,
            "spdMul": 0.667629599571228,
            "type": 0
        },
        {
            "atkMul": 0.6222424507141113,
            "flavorText": "",
            "hpMul": 0.7393704056739807,
            "id": 60,
            "name": "拡張基板 (Lv10)",
            "rarity": 2,
            "spdMul": 0.7759729027748108,
            "type": 1
        },
        {
            "atkMul": 0.21083039045333862,
            "flavorText": "",
            "hpMul": 0.21083039045333862,
            "id": 61,
            "name": "冷却ファン (Lv5)",
            "rarity": 0,
            "spdMul": 0.23718419671058655,
            "type": 3
        },
        {
            "atkMul": 0.7133095264434814,
            "flavorText": "",
            "hpMul": 0.7005718350410461,
            "id": 62,
            "name": "USBメモリ (Lv12)",
            "rarity": 1,
            "spdMul": 0.726047158241272,
            "type": 0
        },
        {
            "atkMul": 0.5626919865608215,
            "flavorText": "",
            "hpMul": 0.444794625043869,
            "id": 63,
            "name": "LANケーブル (Lv10)",
            "rarity": 0,
            "spdMul": 0.48766639828681946,
            "type": 4
        },
        {
            "atkMul": 0.5316100120544434,
            "flavorText": "",
            "hpMul": 0.5980612635612488,
            "id": 64,
            "name": "拡張基板 (Lv13)",
            "rarity": 0,
            "spdMul": 0.6047064065933228,
            "type": 1
        },
        {
            "atkMul": 1.1662195920944214,
            "flavorText": "",
            "hpMul": 0.797415018081665,
            "id": 65,
            "name": "LANケーブル (Lv13)",
            "rarity": 1,
            "spdMul": 0.9768334031105042,
            "type": 4
        },
        {
            "atkMul": 1.5556024312973022,
            "flavorText": "",
            "hpMul": 1.2392085790634155,
            "id": 66,
            "name": "LANケーブル (Lv18)",
            "rarity": 1,
            "spdMul": 1.1469271183013916,
            "type": 4
        },
        {
            "atkMul": 0.8060965538024902,
            "flavorText": "",
            "hpMul": 0.7099565863609314,
            "id": 67,
            "name": "コンデンサ (Lv9)",
            "rarity": 1,
            "spdMul": 0.687770426273346,
            "type": 2
        },
        {
            "atkMul": 0.721103310585022,
            "flavorText": "",
            "hpMul": 0.5159618258476257,
            "id": 68,
            "name": "拡張基板 (Lv12)",
            "rarity": 0,
            "spdMul": 0.49731260538101196,
            "type": 1
        },
        {
            "atkMul": 0.09539999812841415,
            "flavorText": "",
            "hpMul": 0.07560000568628311,
            "id": 69,
            "name": "拡張基板 (Lv2)",
            "rarity": 0,
            "spdMul": 0.10080000758171082,
            "type": 1
        },
        {
            "atkMul": 0.20799998939037323,
            "flavorText": "",
            "hpMul": 0.2963999807834625,
            "id": 70,
            "name": "LANケーブル (Lv4)",
            "rarity": 2,
            "spdMul": 0.28859999775886536,
            "type": 4
        },
        {
            "atkMul": 0.15470001101493835,
            "flavorText": "",
            "hpMul": 0.164900004863739,
            "id": 71,
            "name": "冷却ファン (Lv6)",
            "rarity": 0,
            "spdMul": 0.19380000233650208,
            "type": 3
        },
        {
            "atkMul": 0.11050000041723251,
            "flavorText": "",
            "hpMul": 0.133899986743927,
            "id": 72,
            "name": "コンデンサ (Lv4)",
            "rarity": 0,
            "spdMul": 0.15600000321865082,
            "type": 2
        },
        {
            "atkMul": 0.26009997725486755,
            "flavorText": "",
            "hpMul": 0.2498999983072281,
            "id": 73,
            "name": "USBメモリ (Lv6)",
            "rarity": 1,
            "spdMul": 0.2626499831676483,
            "type": 0
        },
        {
            "atkMul": 0.20469999313354492,
            "flavorText": "",
            "hpMul": 0.25759997963905334,
            "id": 74,
            "name": "冷却ファン (Lv9)",
            "rarity": 0,
            "spdMul": 0.27140000462532043,
            "type": 3
        },
        {
            "atkMul": 0.10710000991821289,
            "flavorText": "",
            "hpMul": 0.09630000591278076,
            "id": 75,
            "name": "USBメモリ (Lv2)",
            "rarity": 0,
            "spdMul": 0.08370000123977661,
            "type": 0
        },
        {
            "atkMul": 0.2479500025510788,
            "flavorText": "",
            "hpMul": 0.2565000057220459,
            "id": 76,
            "name": "コンデンサ (Lv7)",
            "rarity": 1,
            "spdMul": 0.2593500018119812,
            "type": 2
        },
        {
            "atkMul": 0.07209999859333038,
            "flavorText": "",
            "hpMul": 0.07909999787807465,
            "id": 77,
            "name": "冷却ファン (Lv1)",
            "rarity": 0,
            "spdMul": 0.06370000541210175,
            "type": 3
        },
        {
            "atkMul": 0.22499999403953552,
            "flavorText": "",
            "hpMul": 0.20249998569488525,
            "id": 78,
            "name": "USBメモリ (Lv10)",
            "rarity": 0,
            "spdMul": 0.23249998688697815,
            "type": 0
        },
        {
            "atkMul": 0.23205000162124634,
            "flavorText": "",
            "hpMul": 0.20474998652935028,
            "id": 79,
            "name": "冷却ファン (Lv4)",
            "rarity": 1,
            "spdMul": 0.22815001010894775,
            "type": 3
        },
        {
            "atkMul": 0.5699999332427979,
            "flavorText": "",
            "hpMul": 0.4899999797344208,
            "id": 80,
            "name": "拡張基板 (Lv10)",
            "rarity": 2,
            "spdMul": 0.5299999117851257,
            "type": 1
        },
        {
            "atkMul": 0.07349999994039536,
            "flavorText": "",
            "hpMul": 0.07419999688863754,
            "id": 81,
            "name": "拡張基板 (Lv1)",
            "rarity": 0,
            "spdMul": 0.06650000065565109,
            "type": 1
        },
        {
            "atkMul": 0.5699999332427979,
            "flavorText": "",
            "hpMul": 0.4899999797344208,
            "id": 82,
            "name": "拡張基板 (Lv10)",
            "rarity": 2,
            "spdMul": 0.5299999117851257,
            "type": 1
        },
        {
            "atkMul": 0.23919998109340668,
            "flavorText": "",
            "hpMul": 0.2092999964952469,
            "id": 83,
            "name": "コンデンサ (Lv9)",
            "rarity": 0,
            "spdMul": 0.18400000035762787,
            "type": 2
        },
        {
            "atkMul": 0.3905999958515167,
            "flavorText": "",
            "hpMul": 0.3401999771595001,
            "id": 84,
            "name": "拡張基板 (Lv8)",
            "rarity": 2,
            "spdMul": 0.4535999894142151,
            "type": 1
        },
        {
            "atkMul": 0.31049999594688416,
            "flavorText": "",
            "hpMul": 0.2897999882698059,
            "id": 85,
            "name": "LANケーブル (Lv9)",
            "rarity": 1,
            "spdMul": 0.3863999545574188,
            "type": 4
        },
        {
            "atkMul": 0.24780000746250153,
            "flavorText": "",
            "hpMul": 0.1826999932527542,
            "id": 86,
            "name": "コンデンサ (Lv8)",
            "rarity": 0,
            "spdMul": 0.1889999955892563,
            "type": 2
        },
        {
            "atkMul": 0.2621999979019165,
            "flavorText": "",
            "hpMul": 0.2506999969482422,
            "id": 87,
            "name": "USBメモリ (Lv9)",
            "rarity": 0,
            "spdMul": 0.27140000462532043,
            "type": 0
        },
        {
            "atkMul": 0.15300001204013824,
            "flavorText": "",
            "hpMul": 0.18360000848770142,
            "id": 88,
            "name": "冷却ファン (Lv6)",
            "rarity": 0,
            "spdMul": 0.1784999966621399,
            "type": 3
        },
        {
            "atkMul": 0.28999999165534973,
            "flavorText": "",
            "hpMul": 0.2149999886751175,
            "id": 89,
            "name": "拡張基板 (Lv10)",
            "rarity": 0,
            "spdMul": 0.29249998927116394,
            "type": 1
        },
        {
            "atkMul": 0.5699999332427979,
            "flavorText": "",
            "hpMul": 0.4899999797344208,
            "id": 90,
            "name": "拡張基板 (Lv10)",
            "rarity": 2,
            "spdMul": 0.5299999117851257,
            "type": 1
        },
        {
            "atkMul": 0.11659999191761017,
            "flavorText": "",
            "hpMul": 0.12539999186992645,
            "id": 91,
            "name": "USBメモリ (Lv3)",
            "rarity": 0,
            "spdMul": 0.10779999941587448,
            "type": 0
        },
        {
            "atkMul": 0.2621999979019165,
            "flavorText": "",
            "hpMul": 0.2506999969482422,
            "id": 92,
            "name": "USBメモリ (Lv9)",
            "rarity": 0,
            "spdMul": 0.27140000462532043,
            "type": 0
        },
        {
            "atkMul": 0.6115999817848206,
            "flavorText": "強力だがウイルスが混入している。",
            "hpMul": -0.10000000149011612,
            "id": 93,
            "name": "[感染] コンデンサ (Lv8)",
            "rarity": 2,
            "spdMul": 0.4535999894142151,
            "type": 2
        },
        {
            "atkMul": 0.20499998331069946,
            "flavorText": "",
            "hpMul": 0.19999998807907104,
            "id": 94,
            "name": "冷却ファン (Lv10)",
            "rarity": 0,
            "spdMul": 0.20499998331069946,
            "type": 3
        },
        {
            "atkMul": 0.0714000016450882,
            "flavorText": "",
            "hpMul": 0.05810000002384186,
            "id": 95,
            "name": "拡張基板 (Lv1)",
            "rarity": 0,
            "spdMul": 0.06300000101327896,
            "type": 1
        },
        {
            "atkMul": 0.5329999923706055,
            "flavorText": "強力だがウイルスが混入している。",
            "hpMul": -0.10000000149011612,
            "id": 96,
            "name": "[感染] LANケーブル (Lv5)",
            "rarity": 2,
            "spdMul": 0.34199997782707214,
            "type": 4
        },
        {
            "atkMul": 0.0999000072479248,
            "flavorText": "",
            "hpMul": 0.0828000083565712,
            "id": 97,
            "name": "LANケーブル (Lv2)",
            "rarity": 0,
            "spdMul": 0.09180000424385071,
            "type": 4
        },
        {
            "atkMul": 0.15839999914169312,
            "flavorText": "",
            "hpMul": 0.1732499897480011,
            "id": 98,
            "name": "LANケーブル (Lv3)",
            "rarity": 1,
            "spdMul": 0.16004998981952667,
            "type": 4
        },
        {
            "atkMul": 0.6370000243186951,
            "flavorText": "強力だがウイルスが混入している。",
            "hpMul": -0.10000000149011612,
            "id": 99,
            "name": "[感染] 拡張基板 (Lv9)",
            "rarity": 2,
            "spdMul": 0.4875999391078949,
            "type": 1
        },
        {
            "atkMul": 0.11659999191761017,
            "flavorText": "",
            "hpMul": 0.12210000306367874,
            "id": 100,
            "name": "USBメモリ (Lv3)",
            "rarity": 0,
            "spdMul": 0.09239999949932098,
            "type": 0
        },
        {
            "atkMul": 0.3035999834537506,
            "flavorText": "",
            "hpMul": 0.31049999594688416,
            "id": 101,
            "name": "LANケーブル (Lv9)",
            "rarity": 1,
            "spdMul": 0.4036499857902527,
            "type": 4
        },
        {
            "atkMul": 0.3035999834537506,
            "flavorText": "",
            "hpMul": 0.31049999594688416,
            "id": 102,
            "name": "LANケーブル (Lv9)",
            "rarity": 1,
            "spdMul": 0.4036499857902527,
            "type": 4
        },
        {
            "atkMul": 0.06650000065565109,
            "flavorText": "",
            "hpMul": 0.07069999724626541,
            "id": 103,
            "name": "コンデンサ (Lv1)",
            "rarity": 0,
            "spdMul": 0.06159999966621399,
            "type": 2
        },
        {
            "atkMul": 0.1018500104546547,
            "flavorText": "",
            "hpMul": 0.08400000631809235,
            "id": 104,
            "name": "コンデンサ (Lv1)",
            "rarity": 1,
            "spdMul": 0.0861000046133995,
            "type": 2
        },
        {
            "atkMul": 0.3937499523162842,
            "flavorText": "",
            "hpMul": 0.3974999487400055,
            "id": 105,
            "name": "LANケーブル (Lv10)",
            "rarity": 1,
            "spdMul": 0.4424999952316284,
            "type": 4
        },
        {
            "atkMul": 0.15300001204013824,
            "flavorText": "",
            "hpMul": 0.18360000848770142,
            "id": 106,
            "name": "冷却ファン (Lv6)",
            "rarity": 0,
            "spdMul": 0.1784999966621399,
            "type": 3
        },
        {
            "atkMul": 0.22049999237060547,
            "flavorText": "",
            "hpMul": 0.23624998331069946,
            "id": 107,
            "name": "LANケーブル (Lv5)",
            "rarity": 1,
            "spdMul": 0.24300000071525574,
            "type": 4
        },
        {
            "atkMul": 0.1822499930858612,
            "flavorText": "",
            "hpMul": 0.26100000739097595,
            "id": 108,
            "name": "冷却ファン (Lv5)",
            "rarity": 1,
            "spdMul": 0.2317499816417694,
            "type": 3
        },
        {
            "atkMul": 0.5444999933242798,
            "flavorText": "",
            "hpMul": 0.445499986410141,
            "id": 109,
            "name": "冷却ファン (Lv5)",
            "rarity": 3,
            "spdMul": 0.40094998478889465,
            "type": 3
        },
        {
            "atkMul": 0.526680052280426,
            "flavorText": "",
            "hpMul": 0.526680052280426,
            "id": 110,
            "name": "拡張基板 (Lv7)",
            "rarity": 3,
            "spdMul": 0.7210500240325928,
            "type": 1
        },
        {
            "atkMul": 0.6388999819755554,
            "flavorText": "強力だがウイルスが混入している。",
            "hpMul": -0.10000000149011612,
            "id": 111,
            "name": "[感染] USBメモリ (Lv8)",
            "rarity": 2,
            "spdMul": 0.4989599883556366,
            "type": 0
        },
        {
            "atkMul": 0.3197700083255768,
            "flavorText": "",
            "hpMul": 0.30723002552986145,
            "id": 112,
            "name": "USBメモリ (Lv7)",
            "rarity": 1,
            "spdMul": 0.3229050040245056,
            "type": 0
        },
        {
            "atkMul": 0.3158099949359894,
            "flavorText": "",
            "hpMul": 0.40293002128601074,
            "id": 113,
            "name": "冷却ファン (Lv3)",
            "rarity": 3,
            "spdMul": 0.38477998971939087,
            "type": 3
        },
        {
            "atkMul": 0.3712499737739563,
            "flavorText": "",
            "hpMul": 0.3464999794960022,
            "id": 114,
            "name": "LANケーブル (Lv10)",
            "rarity": 1,
            "spdMul": 0.46199995279312134,
            "type": 4
        },
        {
            "atkMul": 0.9801000356674194,
            "flavorText": "",
            "hpMul": 0.8731800317764282,
            "id": 115,
            "name": "USBメモリ (Lv11)",
            "rarity": 3,
            "spdMul": 0.9622800946235657,
            "type": 0
        },
        {
            "atkMul": 0.25987496972084045,
            "flavorText": "",
            "hpMul": 0.2400749921798706,
            "id": 116,
            "name": "拡張基板 (Lv5)",
            "rarity": 1,
            "spdMul": 0.2301749885082245,
            "type": 1
        },
        {
            "atkMul": 0.1985500156879425,
            "flavorText": "",
            "hpMul": 0.19228000938892365,
            "id": 117,
            "name": "冷却ファン (Lv7)",
            "rarity": 0,
            "spdMul": 0.19437000155448914,
            "type": 3
        },
        {
            "atkMul": 0.09405001252889633,
            "flavorText": "",
            "hpMul": 0.09999000281095505,
            "id": 118,
            "name": "コンデンサ (Lv2)",
            "rarity": 0,
            "spdMul": 0.08712000399827957,
            "type": 2
        },
        {
            "atkMul": 0.09405001252889633,
            "flavorText": "",
            "hpMul": 0.09999000281095505,
            "id": 119,
            "name": "コンデンサ (Lv2)",
            "rarity": 0,
            "spdMul": 0.08712000399827957,
            "type": 2
        },
        {
            "atkMul": 0.24354001879692078,
            "flavorText": "",
            "hpMul": 0.23760001361370087,
            "id": 120,
            "name": "冷却ファン (Lv11)",
            "rarity": 0,
            "spdMul": 0.24354001879692078,
            "type": 3
        },
        {
            "atkMul": 0.18149998784065247,
            "flavorText": "",
            "hpMul": 0.1418999880552292,
            "id": 121,
            "name": "コンデンサ (Lv5)",
            "rarity": 0,
            "spdMul": 0.13364998996257782,
            "type": 2
        },
        {
            "atkMul": 0.19019001722335815,
            "flavorText": "",
            "hpMul": 0.20273001492023468,
            "id": 122,
            "name": "冷却ファン (Lv7)",
            "rarity": 0,
            "spdMul": 0.23826000094413757,
            "type": 3
        },
        {
            "atkMul": 0.19437000155448914,
            "flavorText": "",
            "hpMul": 0.24035000801086426,
            "id": 123,
            "name": "冷却ファン (Lv7)",
            "rarity": 0,
            "spdMul": 0.1818300038576126,
            "type": 3
        },
        {
            "atkMul": 0.3088800013065338,
            "flavorText": "",
            "hpMul": 0.2762100100517273,
            "id": 124,
            "name": "冷却ファン (Lv11)",
            "rarity": 0,
            "spdMul": 0.3088800013065338,
            "type": 3
        },
        {
            "atkMul": 0.18700000643730164,
            "flavorText": "",
            "hpMul": 0.19634999334812164,
            "id": 125,
            "name": "コンデンサ (Lv6)",
            "rarity": 0,
            "spdMul": 0.21879002451896667,
            "type": 2
        },
        {
            "atkMul": 0.3222449719905853,
            "flavorText": "",
            "hpMul": 0.41233500838279724,
            "id": 126,
            "name": "USBメモリ (Lv8)",
            "rarity": 1,
            "spdMul": 0.33610498905181885,
            "type": 0
        },
        {
            "atkMul": 0.38896000385284424,
            "flavorText": "",
            "hpMul": 0.4413200318813324,
            "id": 127,
            "name": "LANケーブル (Lv6)",
            "rarity": 2,
            "spdMul": 0.3926999866962433,
            "type": 4
        },
        {
            "atkMul": 0.21504999697208405,
            "flavorText": "",
            "hpMul": 0.1552100032567978,
            "id": 128,
            "name": "LANケーブル (Lv6)",
            "rarity": 0,
            "spdMul": 0.1851300150156021,
            "type": 4
        },
        {
            "atkMul": 0.43312492966651917,
            "flavorText": "",
            "hpMul": 0.45374998450279236,
            "id": 129,
            "name": "LANケーブル (Lv10)",
            "rarity": 1,
            "spdMul": 0.3712499737739563,
            "type": 4
        },
        {
            "atkMul": 0.5732979774475098,
            "flavorText": "",
            "hpMul": 0.45084598660469055,
            "id": 130,
            "name": "コンデンサ (Lv9)",
            "rarity": 2,
            "spdMul": 0.6679199934005737,
            "type": 2
        },
        {
            "atkMul": 0.3144789934158325,
            "flavorText": "",
            "hpMul": 0.2866489887237549,
            "id": 131,
            "name": "コンデンサ (Lv9)",
            "rarity": 0,
            "spdMul": 0.2393379956483841,
            "type": 2
        },
        {
            "atkMul": 0.2159850001335144,
            "flavorText": "",
            "hpMul": 0.23885399103164673,
            "id": 132,
            "name": "USBメモリ (Lv8)",
            "rarity": 0,
            "spdMul": 0.2947560250759125,
            "type": 0
        },
        {
            "atkMul": 0.20001299679279327,
            "flavorText": "",
            "hpMul": 0.21840500831604004,
            "id": 133,
            "name": "LANケーブル (Lv7)",
            "rarity": 0,
            "spdMul": 0.21610599756240845,
            "type": 4
        },
        {
            "atkMul": 0.8167499303817749,
            "flavorText": "",
            "hpMul": 0.8167499303817749,
            "id": 134,
            "name": "冷却ファン (Lv10)",
            "rarity": 3,
            "spdMul": 1.0617749691009521,
            "type": 3
        },
        {
            "atkMul": 0.4628249406814575,
            "flavorText": "",
            "hpMul": 0.42652496695518494,
            "id": 135,
            "name": "コンデンサ (Lv10)",
            "rarity": 1,
            "spdMul": 0.3856874704360962,
            "type": 2
        },
        {
            "atkMul": 0.3158099949359894,
            "flavorText": "",
            "hpMul": 0.28422901034355164,
            "id": 136,
            "name": "USBメモリ (Lv12)",
            "rarity": 0,
            "spdMul": 0.3263370096683502,
            "type": 0
        },
        {
            "atkMul": 0.22627002000808716,
            "flavorText": "",
            "hpMul": 0.17690201103687286,
            "id": 137,
            "name": "コンデンサ (Lv6)",
            "rarity": 0,
            "spdMul": 0.1666170060634613,
            "type": 2
        },
        {
            "atkMul": 0.7103779911994934,
            "flavorText": "強力だがウイルスが混入している。",
            "hpMul": -0.10000000149011612,
            "id": 138,
            "name": "[感染] LANケーブル (Lv7)",
            "rarity": 2,
            "spdMul": 0.5241720080375671,
            "type": 4
        },
        {
            "atkMul": 0.30764248967170715,
            "flavorText": "",
            "hpMul": 0.32670000195503235,
            "id": 139,
            "name": "USBメモリ (Lv5)",
            "rarity": 1,
            "spdMul": 0.25591498613357544,
            "type": 0
        },
        {
            "atkMul": 0.7096650004386902,
            "flavorText": "",
            "hpMul": 0.7347119450569153,
            "id": 140,
            "name": "拡張基板 (Lv9)",
            "rarity": 3,
            "spdMul": 0.7013159990310669,
            "type": 1
        }
    ],
    "lastSavedTime": 1782892530,
    "maxDeploymentLimit": 50,
    "prestigeCount": 2,
    "prestigePoints": 0,
    "relicEncyclopedia": [
        {
            "description": "保存容量1.44MB。 全体ATK+5%",
            "globalAtkBuff": 0.05000000074505806,
            "globalHpBuff": 0.0,
            "globalSpdBuff": 0.0,
            "id": 0,
            "isUnlocked": true,
            "name": "フロッピーディスク"
        },
        {
            "description": "黒画面と緑の文字。 全体HP+5%",
            "globalAtkBuff": 0.0,
            "globalHpBuff": 0.05000000074505806,
            "globalSpdBuff": 0.0,
            "id": 1,
            "isUnlocked": true,
            "name": "MS-DOS画面"
        },
        {
            "description": "接続時のあの音。 全体SPD+5%",
            "globalAtkBuff": 0.0,
            "globalHpBuff": 0.0,
            "globalSpdBuff": 0.05000000074505806,
            "id": 2,
            "isUnlocked": true,
            "name": "ダイヤルアップ音"
        },
        {
            "description": "重くてデカい。 全体HP+10%",
            "globalAtkBuff": 0.0,
            "globalHpBuff": 0.10000000149011612,
            "globalSpdBuff": 0.0,
            "id": 3,
            "isUnlocked": true,
            "name": "ブラウン管モニタ"
        },
        {
            "description": "もう開くことはない。 全体ATK+10%",
            "globalAtkBuff": 0.10000000149011612,
            "globalHpBuff": 0.0,
            "globalSpdBuff": 0.0,
            "id": 4,
            "isUnlocked": true,
            "name": "IEショートカット"
        }
    ],
    "skillLevelAtk": 0,
    "skillLevelGold": 0,
    "skillLevelHp": 0,
    "skillLevelSpd": 1,
    "themeOwned": [
        true,
        false,
        false,
        true
    ],
    "totalDamage": 263416251.22647357,
    "totalGoldEarned": 1.6000000018066992e+16,
    "totalItems": 0,
    "totalKills": 243
}